visualkeras/__init__.py
visualkeras/graph.py
visualkeras/layer_utils.py
visualkeras/layered.py
visualkeras/options.py
visualkeras/utils.py
visualkeras-0.2.0.dist-info/licenses/LICENSE
visualkeras-0.2.0.dist-info/METADATA
visualkeras-0.2.0.dist-info/WHEEL
visualkeras-0.2.0.dist-info/top_level.txt
visualkeras-0.2.0.dist-info/RECORD
