Metadata-Version: 2.4
Name: visualkeras
Version: 0.2.0
Summary: Architecture visualization of Keras models
Home-page: https://github.com/paulgavrikov/visualkeras
Author: Paul Gavrikov
Author-email: paul.gavrikov@hs-offenburg.de
Classifier: Programming Language :: Python :: 3
Classifier: License :: OSI Approved :: MIT License
Classifier: Operating System :: OS Independent
Requires-Python: >=3.6
License-File: LICENSE
Requires-Dist: pillow>=6.2.0
Requires-Dist: numpy>=1.18.1
Requires-Dist: aggdraw>=1.3.11
Dynamic: author
Dynamic: author-email
Dynamic: classifier
Dynamic: description
Dynamic: description-content-type
Dynamic: home-page
Dynamic: license-file
Dynamic: requires-dist
Dynamic: requires-python
Dynamic: summary
